tail.py
tail-0.1.11.dist-info/LICENSE
tail-0.1.11.dist-info/METADATA
tail-0.1.11.dist-info/WHEEL
tail-0.1.11.dist-info/entry_points.txt
tail-0.1.11.dist-info/top_level.txt
tail-0.1.11.dist-info/RECORD
