Metadata-Version: 2.1
Name: tail
Version: 0.1.11
Summary: 文件tail工具。引入“偏移量文件”记录文件读取信息，支持文件内容断续读取。
Home-page: https://github.com/appstore-zencore/tail
Author: zencore
Author-email: dobetter@zencore.cn
License: MIT
Keywords: tail,tailf,pytail
Platform: UNKNOWN
Classifier: Development Status :: 5 - Production/Stable
Classifier: Intended Audience :: Developers
Classifier: Topic :: Software Development :: Libraries :: Python Modules
Classifier: License :: OSI Approved :: MIT License
Classifier: Programming Language :: Python :: 3
Classifier: Programming Language :: Python :: 3 :: Only
Requires-Dist: click
Requires-Dist: pywin32
